dev_cleaner/__init__.py
dev_cleaner/__main__.py
dev_cleaner/cli.py
dev_cleaner/py.typed
dev_cleaner/cleaners/__init__.py
dev_cleaner/cleaners/cargo.py
dev_cleaner/cleaners/claude.py
dev_cleaner/cleaners/cocoapods.py
dev_cleaner/cleaners/docker.py
dev_cleaner/cleaners/go.py
dev_cleaner/cleaners/gradle.py
dev_cleaner/cleaners/homebrew.py
dev_cleaner/cleaners/npm.py
dev_cleaner/cleaners/pip.py
dev_cleaner/cleaners/pnpm.py
dev_cleaner/cleaners/uv.py
dev_cleaner/cleaners/yarn.py
dev_cleaner/core/__init__.py
dev_cleaner/core/base.py
dev_cleaner/core/executor.py
dev_cleaner/core/registry.py
dev_cleaner/core/scanner.py
dev_cleaner/ui/__init__.py
dev_cleaner/ui/console.py
dev_cleaner-0.1.0.dist-info/METADATA
dev_cleaner-0.1.0.dist-info/WHEEL
dev_cleaner-0.1.0.dist-info/entry_points.txt
dev_cleaner-0.1.0.dist-info/licenses/LICENSE
dev_cleaner-0.1.0.dist-info/RECORD
