Metadata-Version: 2.4
Name: dev-cleaner
Version: 0.1.0
Summary: CLI tool to clean development caches and free disk space
Project-URL: Homepage, https://github.com/elexingyu/dev-cleaner
Project-URL: Repository, https://github.com/elexingyu/dev-cleaner
Project-URL: Issues, https://github.com/elexingyu/dev-cleaner/issues
Author-email: elexingyu <elexingyu@gmail.com>
License-Expression: MIT
License-File: LICENSE
Keywords: cache,cargo,cleanup,cli,development,disk-space,docker,homebrew,npm,pip
Classifier: Development Status :: 4 - Beta
Classifier: Environment :: Console
Classifier: Intended Audience :: Developers
Classifier: License :: OSI Approved :: MIT License
Classifier: Operating System :: MacOS
Classifier: Operating System :: POSIX :: Linux
Classifier: Programming Language :: Python :: 3
Classifier: Programming Language :: Python :: 3.10
Classifier: Programming Language :: Python :: 3.11
Classifier: Programming Language :: Python :: 3.12
Classifier: Programming Language :: Python :: 3.13
Classifier: Topic :: System :: Systems Administration
Classifier: Topic :: Utilities
Classifier: Typing :: Typed
Requires-Python: >=3.10
Requires-Dist: rich>=13.0.0
Requires-Dist: typer>=0.9.0
